{
  "__inputs": [
    {
      "name": "DS_INFLUXDB",
      "label": "InfluxDB",
      "description": "",
      "type": "datasource",
      "pluginId": "influxdb",
      "pluginName": "InfluxDB"
    }
  ],
  "__elements": [],
  "__requires": [
    {
      "type": "grafana",
      "id": "grafana",
      "name": "Grafana",
      "version": "8.3.6"
    },
    {
      "type": "panel",
      "id": "graph",
      "name": "Graph (old)",
      "version": ""
    },
    {
      "type": "datasource",
      "id": "influxdb",
      "name": "InfluxDB",
      "version": "1.0.0"
    },
    {
      "type": "panel",
      "id": "stat",
      "name": "Stat",
      "version": ""
    },
    {
      "type": "panel",
      "id": "timeseries",
      "name": "Time series",
      "version": ""
    }
  ],
  "annotations": {
    "list": [
      {
        "builtIn": 1,
        "datasource": "-- Grafana --",
        "enable": true,
        "hide": true,
        "iconColor": "rgba(0, 211, 255, 1)",
        "name": "Annotations & Alerts",
        "target": {
          "limit": 100,
          "matchAny": false,
          "tags": [],
          "type": "dashboard"
        },
        "type": "dashboard"
      }
    ]
  },
  "editable": true,
  "fiscalYearStartMonth": 0,
  "graphTooltip": 0,
  "id": null,
  "links": [],
  "liveNow": false,
  "panels": [
    {
      "alert": {
        "alertRuleTags": {},
        "conditions": [
          {
            "evaluator": {
              "params": [
                90
              ],
              "type": "gt"
            },
            "operator": {
              "type": "and"
            },
            "query": {
              "params": [
                "A",
                "5m",
                "now"
              ]
            },
            "reducer": {
              "params": [],
              "type": "avg"
            },
            "type": "query"
          }
        ],
        "executionErrorState": "alerting",
        "for": "5m",
        "frequency": "1m",
        "handler": 1,
        "name": "Zetachain CPU Utilization alert",
        "noDataState": "no_data",
        "notifications": [
          {
            "uid": "1-61ArEVz"
          }
        ]
      },
      "aliasColors": {},
      "bars": false,
      "dashLength": 10,
      "dashes": false,
      "fieldConfig": {
        "defaults": {
          "unit": "percent"
        },
        "overrides": []
      },
      "fill": 1,
      "fillGradient": 0,
      "gridPos": {
        "h": 7,
        "w": 6,
        "x": 0,
        "y": 0
      },
      "hiddenSeries": false,
      "id": 2,
      "legend": {
        "avg": false,
        "current": false,
        "max": false,
        "min": false,
        "show": false,
        "total": false,
        "values": false
      },
      "lines": true,
      "linewidth": 1,
      "nullPointMode": "null",
      "options": {
        "alertThreshold": true
      },
      "percentage": false,
      "pluginVersion": "8.3.6",
      "pointradius": 2,
      "points": false,
      "renderer": "flot",
      "seriesOverrides": [],
      "spaceLength": 10,
      "stack": false,
      "steppedLine": false,
      "targets": [
        {
          "alias": "CPU Utilization",
          "datasource": {
            "type": "influxdb",
            "uid": "${DS_INFLUXDB}"
          },
          "groupBy": [
            {
              "params": [
                "1m"
              ],
              "type": "time"
            },
            {
              "params": [
                "null"
              ],
              "type": "fill"
            }
          ],
          "measurement": "cpu",
          "orderByTime": "ASC",
          "policy": "default",
          "refId": "A",
          "resultFormat": "time_series",
          "select": [
            [
              {
                "params": [
                  "usage_idle"
                ],
                "type": "field"
              },
              {
                "params": [],
                "type": "mean"
              },
              {
                "params": [
                  "* -1 +100"
                ],
                "type": "math"
              }
            ]
          ],
          "tags": [
            {
              "key": "host",
              "operator": "=",
              "value": "zetachain-testnet-validator"
            }
          ]
        }
      ],
      "thresholds": [
        {
          "colorMode": "critical",
          "fill": true,
          "line": true,
          "op": "gt",
          "value": 90,
          "visible": true
        }
      ],
      "timeRegions": [],
      "title": "CPU Utilization",
      "tooltip": {
        "shared": true,
        "sort": 0,
        "value_type": "individual"
      },
      "type": "graph",
      "xaxis": {
        "mode": "time",
        "show": true,
        "values": []
      },
      "yaxes": [
        {
          "$$hashKey": "object:1433",
          "format": "percent",
          "logBase": 1,
          "max": "100",
          "min": "0",
          "show": true
        },
        {
          "$$hashKey": "object:1434",
          "format": "short",
          "logBase": 1,
          "show": true
        }
      ],
      "yaxis": {
        "align": false
      }
    },
    {
      "alert": {
        "alertRuleTags": {},
        "conditions": [
          {
            "evaluator": {
              "params": [
                90
              ],
              "type": "gt"
            },
            "operator": {
              "type": "and"
            },
            "query": {
              "params": [
                "A",
                "5m",
                "now"
              ]
            },
            "reducer": {
              "params": [],
              "type": "avg"
            },
            "type": "query"
          }
        ],
        "executionErrorState": "alerting",
        "for": "5m",
        "frequency": "1m",
        "handler": 1,
        "name": "Zetachain Memory Utilization alert",
        "noDataState": "no_data",
        "notifications": [
          {
            "uid": "1-61ArEVz"
          }
        ]
      },
      "aliasColors": {},
      "bars": false,
      "dashLength": 10,
      "dashes": false,
      "fieldConfig": {
        "defaults": {
          "unit": "percent"
        },
        "overrides": []
      },
      "fill": 1,
      "fillGradient": 0,
      "gridPos": {
        "h": 7,
        "w": 6,
        "x": 6,
        "y": 0
      },
      "hiddenSeries": false,
      "id": 4,
      "legend": {
        "avg": false,
        "current": false,
        "max": false,
        "min": false,
        "show": false,
        "total": false,
        "values": false
      },
      "lines": true,
      "linewidth": 1,
      "nullPointMode": "null",
      "options": {
        "alertThreshold": true
      },
      "percentage": false,
      "pluginVersion": "8.3.6",
      "pointradius": 2,
      "points": false,
      "renderer": "flot",
      "seriesOverrides": [],
      "spaceLength": 10,
      "stack": false,
      "steppedLine": false,
      "targets": [
        {
          "alias": "RAM Utilization",
          "datasource": {
            "type": "influxdb",
            "uid": "${DS_INFLUXDB}"
          },
          "groupBy": [
            {
              "params": [
                "1m"
              ],
              "type": "time"
            },
            {
              "params": [
                "null"
              ],
              "type": "fill"
            }
          ],
          "measurement": "mem",
          "orderByTime": "ASC",
          "policy": "default",
          "refId": "A",
          "resultFormat": "time_series",
          "select": [
            [
              {
                "params": [
                  "used_percent"
                ],
                "type": "field"
              },
              {
                "params": [],
                "type": "mean"
              }
            ]
          ],
          "tags": [
            {
              "key": "host",
              "operator": "=",
              "value": "zetachain-testnet-validator"
            }
          ]
        }
      ],
      "thresholds": [
        {
          "colorMode": "critical",
          "fill": true,
          "line": true,
          "op": "gt",
          "value": 90,
          "visible": true
        }
      ],
      "timeRegions": [],
      "title": "Memory Utilization",
      "tooltip": {
        "shared": true,
        "sort": 0,
        "value_type": "individual"
      },
      "type": "graph",
      "xaxis": {
        "mode": "time",
        "show": true,
        "values": []
      },
      "yaxes": [
        {
          "$$hashKey": "object:1332",
          "format": "percent",
          "logBase": 1,
          "max": "100",
          "min": "0",
          "show": true
        },
        {
          "$$hashKey": "object:1333",
          "format": "short",
          "logBase": 1,
          "show": true
        }
      ],
      "yaxis": {
        "align": false
      }
    },
    {
      "alert": {
        "alertRuleTags": {},
        "conditions": [
          {
            "evaluator": {
              "params": [
                2000000000
              ],
              "type": "lt"
            },
            "operator": {
              "type": "and"
            },
            "query": {
              "params": [
                "A",
                "5m",
                "now"
              ]
            },
            "reducer": {
              "params": [],
              "type": "avg"
            },
            "type": "query"
          },
          {
            "evaluator": {
              "params": [
                10000000000
              ],
              "type": "gt"
            },
            "operator": {
              "type": "and"
            },
            "query": {
              "params": [
                "B",
                "5m",
                "now"
              ]
            },
            "reducer": {
              "params": [],
              "type": "avg"
            },
            "type": "query"
          }
        ],
        "executionErrorState": "alerting",
        "for": "5m",
        "frequency": "1m",
        "handler": 1,
        "name": "Zetachain Free Disk Space alert",
        "noDataState": "no_data",
        "notifications": [
          {
            "uid": "1-61ArEVz"
          }
        ]
      },
      "aliasColors": {},
      "bars": false,
      "dashLength": 10,
      "dashes": false,
      "fieldConfig": {
        "defaults": {
          "unit": "decbytes"
        },
        "overrides": []
      },
      "fill": 1,
      "fillGradient": 1,
      "gridPos": {
        "h": 7,
        "w": 6,
        "x": 12,
        "y": 0
      },
      "hiddenSeries": false,
      "id": 6,
      "legend": {
        "alignAsTable": true,
        "avg": false,
        "current": true,
        "max": false,
        "min": false,
        "rightSide": true,
        "show": true,
        "total": false,
        "values": true
      },
      "lines": true,
      "linewidth": 1,
      "nullPointMode": "null",
      "options": {
        "alertThreshold": true
      },
      "percentage": false,
      "pluginVersion": "8.3.6",
      "pointradius": 2,
      "points": false,
      "renderer": "flot",
      "seriesOverrides": [],
      "spaceLength": 10,
      "stack": false,
      "steppedLine": false,
      "targets": [
        {
          "alias": "/",
          "datasource": {
            "type": "influxdb",
            "uid": "${DS_INFLUXDB}"
          },
          "groupBy": [
            {
              "params": [
                "5m"
              ],
              "type": "time"
            },
            {
              "params": [
                "null"
              ],
              "type": "fill"
            }
          ],
          "measurement": "disk",
          "orderByTime": "ASC",
          "policy": "default",
          "refId": "A",
          "resultFormat": "time_series",
          "select": [
            [
              {
                "params": [
                  "free"
                ],
                "type": "field"
              },
              {
                "params": [],
                "type": "mean"
              }
            ]
          ],
          "tags": [
            {
              "key": "host",
              "operator": "=",
              "value": "zetachain-testnet-validator"
            },
            {
              "condition": "AND",
              "key": "path",
              "operator": "=",
              "value": "/"
            }
          ]
        },
        {
          "alias": "/data",
          "datasource": {
            "type": "influxdb",
            "uid": "${DS_INFLUXDB}"
          },
          "groupBy": [
            {
              "params": [
                "5m"
              ],
              "type": "time"
            },
            {
              "params": [
                "null"
              ],
              "type": "fill"
            }
          ],
          "hide": false,
          "measurement": "disk",
          "orderByTime": "ASC",
          "policy": "default",
          "refId": "B",
          "resultFormat": "time_series",
          "select": [
            [
              {
                "params": [
                  "free"
                ],
                "type": "field"
              },
              {
                "params": [],
                "type": "mean"
              }
            ]
          ],
          "tags": [
            {
              "key": "host",
              "operator": "=",
              "value": "zetachain-testnet-validator"
            },
            {
              "condition": "AND",
              "key": "path",
              "operator": "=",
              "value": "/data"
            }
          ]
        }
      ],
      "thresholds": [
        {
          "colorMode": "critical",
          "fill": true,
          "line": true,
          "op": "lt",
          "value": 2000000000,
          "visible": true
        }
      ],
      "timeRegions": [],
      "title": "Free Disk Space",
      "tooltip": {
        "shared": true,
        "sort": 0,
        "value_type": "individual"
      },
      "type": "graph",
      "xaxis": {
        "mode": "time",
        "show": true,
        "values": []
      },
      "yaxes": [
        {
          "$$hashKey": "object:771",
          "format": "decbytes",
          "logBase": 1,
          "min": "0",
          "show": true
        },
        {
          "$$hashKey": "object:772",
          "format": "short",
          "logBase": 1,
          "show": true
        }
      ],
      "yaxis": {
        "align": false
      }
    },
    {
      "alert": {
        "alertRuleTags": {},
        "conditions": [
          {
            "evaluator": {
              "params": [
                0
              ],
              "type": "gt"
            },
            "operator": {
              "type": "and"
            },
            "query": {
              "params": [
                "A",
                "5m",
                "now"
              ]
            },
            "reducer": {
              "params": [],
              "type": "avg"
            },
            "type": "query"
          }
        ],
        "executionErrorState": "alerting",
        "for": "5m",
        "frequency": "1m",
        "handler": 1,
        "name": "Zetachain Service Status alert",
        "noDataState": "no_data",
        "notifications": [
          {
            "uid": "1-61ArEVz"
          }
        ]
      },
      "aliasColors": {},
      "bars": false,
      "dashLength": 10,
      "dashes": false,
      "description": "0 - Active",
      "fill": 1,
      "fillGradient": 0,
      "gridPos": {
        "h": 7,
        "w": 6,
        "x": 18,
        "y": 0
      },
      "hiddenSeries": false,
      "id": 8,
      "legend": {
        "avg": false,
        "current": false,
        "max": false,
        "min": false,
        "show": false,
        "total": false,
        "values": false
      },
      "lines": true,
      "linewidth": 1,
      "nullPointMode": "null",
      "options": {
        "alertThreshold": true
      },
      "percentage": false,
      "pluginVersion": "8.3.6",
      "pointradius": 2,
      "points": false,
      "renderer": "flot",
      "seriesOverrides": [],
      "spaceLength": 10,
      "stack": false,
      "steppedLine": false,
      "targets": [
        {
          "alias": "service_status_code",
          "datasource": {
            "type": "influxdb",
            "uid": "${DS_INFLUXDB}"
          },
          "groupBy": [],
          "measurement": "systemd_units",
          "orderByTime": "ASC",
          "policy": "default",
          "refId": "A",
          "resultFormat": "time_series",
          "select": [
            [
              {
                "params": [
                  "active_code"
                ],
                "type": "field"
              }
            ]
          ],
          "tags": [
            {
              "key": "host",
              "operator": "=",
              "value": "zetachain-testnet-validator"
            }
          ]
        }
      ],
      "thresholds": [
        {
          "colorMode": "critical",
          "fill": true,
          "line": true,
          "op": "gt",
          "value": 0,
          "visible": true
        }
      ],
      "timeRegions": [],
      "title": "Service Status",
      "tooltip": {
        "shared": true,
        "sort": 0,
        "value_type": "individual"
      },
      "type": "graph",
      "xaxis": {
        "mode": "time",
        "show": true,
        "values": []
      },
      "yaxes": [
        {
          "$$hashKey": "object:891",
          "format": "short",
          "logBase": 1,
          "min": "0",
          "show": true
        },
        {
          "$$hashKey": "object:892",
          "format": "short",
          "logBase": 1,
          "show": true
        }
      ],
      "yaxis": {
        "align": false
      }
    },
    {
      "alert": {
        "alertRuleTags": {},
        "conditions": [
          {
            "evaluator": {
              "params": [
                0
              ],
              "type": "gt"
            },
            "operator": {
              "type": "and"
            },
            "query": {
              "params": [
                "A",
                "5m",
                "now"
              ]
            },
            "reducer": {
              "params": [],
              "type": "avg"
            },
            "type": "query"
          }
        ],
        "executionErrorState": "alerting",
        "for": "5m",
        "frequency": "1m",
        "handler": 1,
        "name": "Zetachain RPC status alert",
        "noDataState": "alerting",
        "notifications": [
          {
            "uid": "1-61ArEVz"
          }
        ]
      },
      "aliasColors": {},
      "bars": false,
      "dashLength": 10,
      "dashes": false,
      "description": "0 - listening\n\nno data - syncing",
      "fill": 1,
      "fillGradient": 0,
      "gridPos": {
        "h": 7,
        "w": 6,
        "x": 0,
        "y": 7
      },
      "hiddenSeries": false,
      "id": 10,
      "legend": {
        "avg": false,
        "current": false,
        "max": false,
        "min": false,
        "show": false,
        "total": false,
        "values": false
      },
      "lines": true,
      "linewidth": 1,
      "nullPointMode": "null",
      "options": {
        "alertThreshold": true
      },
      "percentage": false,
      "pluginVersion": "8.3.6",
      "pointradius": 2,
      "points": false,
      "renderer": "flot",
      "seriesOverrides": [],
      "spaceLength": 10,
      "stack": false,
      "steppedLine": false,
      "targets": [
        {
          "datasource": {
            "type": "influxdb",
            "uid": "${DS_INFLUXDB}"
          },
          "groupBy": [
            {
              "params": [
                "1m"
              ],
              "type": "time"
            },
            {
              "params": [
                "null"
              ],
              "type": "fill"
            }
          ],
          "measurement": "http",
          "orderByTime": "ASC",
          "policy": "default",
          "refId": "A",
          "resultFormat": "time_series",
          "select": [
            [
              {
                "params": [
                  "catching_up"
                ],
                "type": "field"
              },
              {
                "params": [],
                "type": "mean"
              }
            ]
          ],
          "tags": [
            {
              "key": "components",
              "operator": "=",
              "value": "syncing"
            },
            {
              "condition": "AND",
              "key": "host",
              "operator": "=",
              "value": "zetachain-testnet-validator"
            }
          ]
        }
      ],
      "thresholds": [
        {
          "colorMode": "critical",
          "fill": true,
          "line": true,
          "op": "gt",
          "value": 0,
          "visible": true
        }
      ],
      "timeRegions": [],
      "title": "RPC status",
      "tooltip": {
        "shared": true,
        "sort": 0,
        "value_type": "individual"
      },
      "type": "graph",
      "xaxis": {
        "mode": "time",
        "show": true,
        "values": []
      },
      "yaxes": [
        {
          "$$hashKey": "object:891",
          "format": "short",
          "logBase": 1,
          "min": "0",
          "show": true
        },
        {
          "$$hashKey": "object:892",
          "format": "short",
          "logBase": 1,
          "show": true
        }
      ],
      "yaxis": {
        "align": false
      }
    },
    {
      "alert": {
        "alertRuleTags": {},
        "conditions": [
          {
            "evaluator": {
              "params": [
                0
              ],
              "type": "lt"
            },
            "operator": {
              "type": "and"
            },
            "query": {
              "params": [
                "A",
                "5m",
                "now"
              ]
            },
            "reducer": {
              "params": [],
              "type": "avg"
            },
            "type": "query"
          }
        ],
        "executionErrorState": "alerting",
        "for": "5m",
        "frequency": "1m",
        "handler": 1,
        "name": "Zetachain blocks/min alert",
        "noDataState": "no_data",
        "notifications": [
          {
            "uid": "1-61ArEVz"
          }
        ]
      },
      "aliasColors": {},
      "bars": false,
      "dashLength": 10,
      "dashes": false,
      "fill": 1,
      "fillGradient": 0,
      "gridPos": {
        "h": 7,
        "w": 6,
        "x": 6,
        "y": 7
      },
      "hiddenSeries": false,
      "id": 12,
      "legend": {
        "avg": false,
        "current": false,
        "max": false,
        "min": false,
        "show": false,
        "total": false,
        "values": false
      },
      "lines": true,
      "linewidth": 1,
      "nullPointMode": "null",
      "options": {
        "alertThreshold": true
      },
      "percentage": false,
      "pluginVersion": "8.3.6",
      "pointradius": 2,
      "points": false,
      "renderer": "flot",
      "seriesOverrides": [],
      "spaceLength": 10,
      "stack": false,
      "steppedLine": false,
      "targets": [
        {
          "alias": "blocks per minute",
          "datasource": {
            "type": "influxdb",
            "uid": "${DS_INFLUXDB}"
          },
          "groupBy": [],
          "measurement": "http",
          "orderByTime": "ASC",
          "policy": "default",
          "refId": "A",
          "resultFormat": "time_series",
          "select": [
            [
              {
                "params": [
                  "latest_block_height"
                ],
                "type": "field"
              },
              {
                "params": [
                  "1m"
                ],
                "type": "derivative"
              }
            ]
          ],
          "tags": [
            {
              "key": "host",
              "operator": "=",
              "value": "zetachain-testnet-validator"
            }
          ]
        }
      ],
      "thresholds": [
        {
          "colorMode": "critical",
          "fill": true,
          "line": true,
          "op": "lt",
          "value": 0,
          "visible": true
        }
      ],
      "timeRegions": [],
      "title": "blocks/min",
      "tooltip": {
        "shared": true,
        "sort": 0,
        "value_type": "individual"
      },
      "type": "graph",
      "xaxis": {
        "mode": "time",
        "show": true,
        "values": []
      },
      "yaxes": [
        {
          "$$hashKey": "object:975",
          "format": "short",
          "logBase": 1,
          "min": "0",
          "show": true
        },
        {
          "$$hashKey": "object:976",
          "format": "short",
          "logBase": 1,
          "show": true
        }
      ],
      "yaxis": {
        "align": false
      }
    },
    {
      "alert": {
        "alertRuleTags": {},
        "conditions": [
          {
            "evaluator": {
              "params": [
                500000000000000000
              ],
              "type": "gt"
            },
            "operator": {
              "type": "and"
            },
            "query": {
              "params": [
                "A",
                "5m",
                "now"
              ]
            },
            "reducer": {
              "params": [],
              "type": "avg"
            },
            "type": "query"
          }
        ],
        "executionErrorState": "alerting",
        "for": "5m",
        "frequency": "1m",
        "handler": 1,
        "message": "It's time to delegate tokens to validator.",
        "name": "Zetachain Validator commission alert",
        "noDataState": "no_data",
        "notifications": [
          {
            "uid": "1-61ArEVz"
          }
        ]
      },
      "description": "",
      "fieldConfig": {
        "defaults": {
          "color": {
            "mode": "palette-classic"
          },
          "custom": {
            "axisLabel": "",
            "axisPlacement": "auto",
            "barAlignment": 0,
            "drawStyle": "line",
            "fillOpacity": 25,
            "gradientMode": "none",
            "hideFrom": {
              "legend": false,
              "tooltip": false,
              "viz": false
            },
            "lineInterpolation": "linear",
            "lineWidth": 1,
            "pointSize": 5,
            "scaleDistribution": {
              "type": "linear"
            },
            "showPoints": "auto",
            "spanNulls": false,
            "stacking": {
              "group": "A",
              "mode": "none"
            },
            "thresholdsStyle": {
              "mode": "off"
            }
          },
          "mappings": [],
          "thresholds": {
            "mode": "absolute",
            "steps": [
              {
                "color": "green",
                "value": null
              },
              {
                "color": "red",
                "value": 80
              }
            ]
          },
          "unit": "ZETA"
        },
        "overrides": []
      },
      "gridPos": {
        "h": 7,
        "w": 6,
        "x": 12,
        "y": 7
      },
      "id": 18,
      "options": {
        "legend": {
          "calcs": [
            "lastNotNull"
          ],
          "displayMode": "table",
          "placement": "right"
        },
        "tooltip": {
          "mode": "single"
        }
      },
      "pluginVersion": "8.3.6",
      "targets": [
        {
          "alias": "Comission (ZETA)",
          "datasource": {
            "type": "influxdb",
            "uid": "${DS_INFLUXDB}"
          },
          "groupBy": [],
          "measurement": "exec",
          "orderByTime": "ASC",
          "policy": "default",
          "refId": "A",
          "resultFormat": "time_series",
          "select": [
            [
              {
                "params": [
                  "amount_int"
                ],
                "type": "field"
              },
              {
                "params": [
                  " / 1000000000000000000"
                ],
                "type": "math"
              }
            ]
          ],
          "tags": [
            {
              "key": "host",
              "operator": "=",
              "value": "zetachain-testnet-validator"
            },
            {
              "condition": "AND",
              "key": "api_method",
              "operator": "=",
              "value": "commission"
            }
          ]
        }
      ],
      "thresholds": [
        {
          "colorMode": "critical",
          "op": "gt",
          "value": 500000000000000000,
          "visible": true
        }
      ],
      "title": "Validator commission",
      "type": "timeseries"
    },
    {
      "aliasColors": {},
      "bars": false,
      "dashLength": 10,
      "dashes": false,
      "description": "",
      "fill": 1,
      "fillGradient": 0,
      "gridPos": {
        "h": 7,
        "w": 6,
        "x": 18,
        "y": 7
      },
      "hiddenSeries": false,
      "id": 20,
      "legend": {
        "alignAsTable": true,
        "avg": false,
        "current": true,
        "max": false,
        "min": false,
        "rightSide": true,
        "show": true,
        "total": false,
        "values": true
      },
      "lines": true,
      "linewidth": 1,
      "nullPointMode": "null",
      "options": {
        "alertThreshold": true
      },
      "percentage": false,
      "pluginVersion": "8.3.6",
      "pointradius": 2,
      "points": false,
      "renderer": "flot",
      "seriesOverrides": [],
      "spaceLength": 10,
      "stack": false,
      "steppedLine": false,
      "targets": [
        {
          "alias": "Rewards (ZETA)",
          "datasource": {
            "type": "influxdb",
            "uid": "${DS_INFLUXDB}"
          },
          "groupBy": [],
          "measurement": "exec",
          "orderByTime": "ASC",
          "policy": "default",
          "refId": "A",
          "resultFormat": "time_series",
          "select": [
            [
              {
                "params": [
                  "amount_int"
                ],
                "type": "field"
              },
              {
                "params": [
                  " / 1000000000000000000"
                ],
                "type": "math"
              }
            ]
          ],
          "tags": [
            {
              "key": "host",
              "operator": "=",
              "value": "zetachain-testnet-validator"
            },
            {
              "condition": "AND",
              "key": "api_method",
              "operator": "=",
              "value": "rewards"
            }
          ]
        }
      ],
      "thresholds": [],
      "timeRegions": [],
      "title": "Validator Rewards",
      "tooltip": {
        "shared": true,
        "sort": 0,
        "value_type": "individual"
      },
      "type": "graph",
      "xaxis": {
        "mode": "time",
        "show": true,
        "values": []
      },
      "yaxes": [
        {
          "$$hashKey": "object:2354",
          "format": "ZETA",
          "logBase": 1,
          "show": true
        },
        {
          "$$hashKey": "object:2355",
          "format": "short",
          "logBase": 1,
          "show": true
        }
      ],
      "yaxis": {
        "align": false
      }
    },
    {
      "fieldConfig": {
        "defaults": {
          "color": {
            "mode": "thresholds"
          },
          "mappings": [],
          "thresholds": {
            "mode": "absolute",
            "steps": [
              {
                "color": "green",
                "value": null
              },
              {
                "color": "red",
                "value": 1
              }
            ]
          },
          "unit": "bool_yes_no"
        },
        "overrides": []
      },
      "gridPos": {
        "h": 6,
        "w": 6,
        "x": 0,
        "y": 14
      },
      "id": 16,
      "options": {
        "colorMode": "value",
        "graphMode": "area",
        "justifyMode": "center",
        "orientation": "vertical",
        "reduceOptions": {
          "calcs": [
            "lastNotNull"
          ],
          "fields": "",
          "values": false
        },
        "textMode": "auto"
      },
      "pluginVersion": "8.3.6",
      "targets": [
        {
          "alias": "http request",
          "datasource": {
            "type": "influxdb",
            "uid": "${DS_INFLUXDB}"
          },
          "groupBy": [
            {
              "params": [
                "$__interval"
              ],
              "type": "time"
            },
            {
              "params": [
                "null"
              ],
              "type": "fill"
            }
          ],
          "measurement": "exec",
          "orderByTime": "ASC",
          "policy": "default",
          "refId": "A",
          "resultFormat": "time_series",
          "select": [
            [
              {
                "params": [
                  "jailed"
                ],
                "type": "field"
              },
              {
                "params": [],
                "type": "mean"
              }
            ]
          ],
          "tags": [
            {
              "key": "host",
              "operator": "=",
              "value": "zetachain-testnet-validator"
            },
            {
              "condition": "AND",
              "key": "api_method",
              "operator": "=",
              "value": "jailed_status"
            }
          ]
        }
      ],
      "title": "Jailed status",
      "type": "stat"
    },
    {
      "fieldConfig": {
        "defaults": {
          "color": {
            "mode": "thresholds"
          },
          "mappings": [],
          "thresholds": {
            "mode": "absolute",
            "steps": [
              {
                "color": "green",
                "value": null
              }
            ]
          },
          "unit": "string"
        },
        "overrides": []
      },
      "gridPos": {
        "h": 7,
        "w": 6,
        "x": 6,
        "y": 14
      },
      "id": 14,
      "options": {
        "colorMode": "value",
        "graphMode": "area",
        "justifyMode": "auto",
        "orientation": "auto",
        "reduceOptions": {
          "calcs": [
            "lastNotNull"
          ],
          "fields": "",
          "values": false
        },
        "textMode": "auto"
      },
      "pluginVersion": "8.3.6",
      "targets": [
        {
          "alias": "Block Number",
          "datasource": {
            "type": "influxdb",
            "uid": "${DS_INFLUXDB}"
          },
          "groupBy": [
            {
              "params": [
                "5m"
              ],
              "type": "time"
            },
            {
              "params": [
                "null"
              ],
              "type": "fill"
            }
          ],
          "measurement": "http",
          "orderByTime": "ASC",
          "policy": "default",
          "refId": "A",
          "resultFormat": "time_series",
          "select": [
            [
              {
                "params": [
                  "latest_block_height"
                ],
                "type": "field"
              },
              {
                "params": [],
                "type": "max"
              }
            ]
          ],
          "tags": [
            {
              "key": "host",
              "operator": "=",
              "value": "zetachain-testnet-validator"
            }
          ]
        }
      ],
      "title": "Highest Block Number",
      "type": "stat"
    }
  ],
  "schemaVersion": 34,
  "style": "dark",
  "tags": [
    "project"
  ],
  "templating": {
    "list": []
  },
  "time": {
    "from": "now-6h",
    "to": "now"
  },
  "timepicker": {},
  "timezone": "",
  "title": "Incent | Zetachain Testnet Validator",
  "uid": "3rnFnouVk",
  "version": 6,
  "weekStart": ""
}